{
    "category_name": "World Service",
    "category_item": [
        {
            "item_name": "Radio Mirchi",
            "item_img": "https://content.indiainfoline.com/_media/iifl/img/article/2020-12/07/full/1607334702-2388.png",
            "item_station": [
                {
                    "name": "Radio Mirchi(Official)",
                    "language": "Hindi",
                    "band": "98.3 FM",
                    "location": "Ahmedabad,India",
                    "image": "https://img.etimg.com/thumb/width-1200,height-900,imgsize-42753,resizemode-1,msid-71679895/industry/media/entertainment/radio-mirchi-not-just-a-radio-firm.jpg",
                    "url": "https://radioindia.net/radio/mirchi98/icecast.audio"
                },
                {
                    "name": "Meethi Mirchi",
                    "language": "Hindi",
                    "band": "Online",
                    "location": "Radio Mirchi",
                    "image": "https://media.radiomirchi.com/onlinestation/banners/MeethiMirchi344.jpg",
                    "url": "https://mirchiplaylive.akamaized.net/hls/live/2036929/MUM/MEETHI96kbps.m3u8"
                },
                {
                    "name": "Mirchi 90’s Radio",
                    "language": "Hindi",
                    "band": "Songs",
                    "location": "Mumbai",
                    "image": "https://media.radiomirchi.com/onlinestation/banners/Mirchi90s917.jpg",
                    "url": "https://pehlanashahdlive-lh.akamaihd.net/i/PehlaNashaHDLive_1@335229/master.m3u8"
                },
                {
                    "name": "Mirchi Toota Dil",
                    "language": "Hindi",
                    "band": "98.3 FM",
                    "location": "Radio Mirchi",
                    "image": "https://media.radiomirchi.com/onlinestation/banners/MirchiTootaDil.jpg",
                    "url": "https://tootadil-lh.akamaihd.net/i/tootadil_1@42539/index_1_a-p.m3u8"
                },
                {
                    "name": "Club Mirchi (Party Mix 24x7)",
                    "language": "Hindi",
                    "band": "Online",
                    "location": "Radio Mirchi",
                    "image": "https://media.radiomirchi.com/onlinestation/banners/ClubMirchi165.jpg",
                    "url": "https://mirchiplaylive.akamaized.net/hls/live/2036929/MUM/CLUBMI96kbps.m3u8"
                },
                {
                    "name": "Mirchi Top 20",
                    "language": "Hindi",
                    "band": "Online",
                    "location": "Radio Mirchi",
                    "image": "https://media.radiomirchi.com/onlinestation/banners/MirchiTop20651.jpg",
                    "url": "https://mt20live-lh.akamaihd.net/i/mt20live_1@346531/master.m3u8"
                },
                {
                    "name": "FILMY MIRCHI",
                    "language": "Hindi",
                    "band": "Online",
                    "location": "Radio Mirchi",
                    "image": "https://media.radiomirchi.com/onlinestation/banners/FilmyMirchi285.jpg",
                    "url": "https://filmymirchihdliv-lh.akamaihd.net/i/FilmyMirchiHDLive_1_1@336266/master.m3u8"
                },
                {
                    "name": "Yo! Punjabi Mirchi - Urban Beat",
                    "language": "Hindi",
                    "band": "Online",
                    "location": "Radio Mirchi",
                    "image": "https://media.radiomirchi.com/onlinestation/banners/Yo!Punjabi980.jpg",
                    "url": "https://yopunjabihdlive-lh.akamaihd.net/i/YoPunjabiHDLive_1_1@345454/master.m3u8"
                },
                {
                    "name": "Mirchi Devraag",
                    "language": "Hindi",
                    "band": "Online",
                    "location": "Radio Mirchi",
                    "image": "https://media.radiomirchi.com/onlinestation/banners/MirchiDevraag277.jpg",
                    "url": "https://devraaghdlive-lh.akamaihd.net/i/DevraagHDLive_1_1@336268/index_1_a-p.m3u8?sd=10&rebase=on"
                },
                {
                    "name": "Mirchi love Hindi",
                    "language": "Hindi",
                    "band": "Online",
                    "location": "Radio Mirchi",
                    "image": "https://a10.gaanacdn.com/gn_img/m_radio_circle/qa4WEkqKP1/qa4WEkqKP1/size_l_1590578471.webp",
                    "url": "https://mirchilove-lh.akamaihd.net/i/MIRCHILOVE_1@32886/index_1_a-p.m3u8?sd=10&rebase=on"
                },
                {
                    "name": "Hindi Retro",
                    "language": "Hindi",
                    "band": "Online",
                    "location": "Radio Mirchi",
                    "image": "https://media.radiomirchi.com/onlinestation/banners/HindiRetro300.jpg",
                    "url": "https://puranijeanshdliv-lh.akamaihd.net/i/PuraniJeansHDLive_1_1@334555/master.m3u8"
                },
                {
                    "name": "MIRCHI Drive",
                    "language": "Hindi",
                    "band": "Online",
                    "location": "Radio Mirchi",
                    "image": "https://media.radiomirchi.com/onlinestation/banners/MirchiDriveRadio-1577700603.jpg",
                    "url": "https://driveradio-lh.akamaihd.net/i/DriveRadio_1@793591/master.m3u8"
                },
                {
                    "name": "Mirchi Campus",
                    "language": "Hindi",
                    "band": "Online",
                    "location": "Radio Mirchi",
                    "image": "https://a10.gaanacdn.com/gn_img/m_radio_circle/01A3mrWNQX/01A3mrWNQX/size_m_1625039987.webp",
                    "url": "https://campusradio-lh.akamaihd.net/i/CampusRadio_1@425040/master.m3u8"
                },
                {
                    "name": "Mirchi Indies",
                    "language": "Hindi",
                    "band": "Online",
                    "location": "Radio Mirchi",
                    "image": "https://media.radiomirchi.com/onlinestation/banners/MirchiIndies344.jpg",
                    "url": "https://meethimirchihdl-lh.akamaihd.net/i/MirchiEdgeHDLive_1_1@336272/index_1_a-p.m3u8?sd=10&rebase=on"
                },
                {
                    "name": "Mirchi Delhi Punjabi",
                    "language": "Hindi",
                    "band": "Online",
                    "location": "Radio Mirchi",
                    "image": "https://a10.gaanacdn.com/gn_img/m_radio_circle/qaLKY23pO4/qaLKY23pO4/size_l_1570442932.webp",
                    "url": "https://delhipunjab-lh.akamaihd.net/i/DelhiPunjab_1@4165/index_1_a-p.m3u8?sd=10&rebase=on"
                },
                {
                    "name": "Mirchi Mehfil Ghazal",
                    "language": "Hindi",
                    "band": "Online",
                    "location": "Radio Mirchi",
                    "image": "https://media.radiomirchi.com/onlinestation/banners/Mehfil-e-Ghazal822.jpg",
                    "url": "https://mirchimahfil-lh.akamaihd.net/i/MirchiMehfl_1@120798/index_1_a-p.m3u8?sd=10&rebase=on"
                },
                {
                    "name": "Mirchi Mumbai Marathi",
                    "language": "Hindi",
                    "band": "Online",
                    "location": "Radio Mirchi",
                    "image": "https://a10.gaanacdn.com/gn_img/m_radio_circle/Oxd3xP3gVY/Oxd3xP3gVY/size_l_1563783320.webp",
                    "url": "https://marathimumbai-lh.akamaihd.net/i/Marathimumbai_1@710773/index_1_a-p.m3u8?sd=10&rebase=on"
                },
                {
                    "name": "Mirchi Tamil Hits",
                    "language": "Tami",
                    "band": "Online",
                    "location": "Radio Mirchi",
                    "image": "https://media.radiomirchi.com/onlinestation/banners/TamilHits235.jpg",
                    "url": "https://mirchitoptucker-lh.akamaihd.net/i/MirchiTopTucker_1_1@66103/index_1_a-p.m3u8?sd=10&rebase=on"
                },
                {
                    "name": "Mirchi Telugu Hits",
                    "language": "Telugu",
                    "band": "Online",
                    "location": "Radio Mirchi",
                    "image": "https://media.radiomirchi.com/onlinestation/banners/TeluguHits756.jpg",
                    "url": "https://mirchitapakahd-lh.akamaihd.net/i/mirchitapakahdlive_1_1@322572/index_1_a-p.m3u8?sd=10&rebase=on"
                },
                {
                    "name": "Mirchi Kannada Hits",
                    "language": "Hindi",
                    "band": "Online",
                    "location": "Radio Mirchi",
                    "image": "https://a10.gaanacdn.com/gn_img/m_radio_circle/Dk9KN2KBx1/Dk9KN2KBx1/size_l_1563783758.webp",
                    "url": "https://kannadahits-lh.akamaihd.net/i/kannadahits_1@492837/index_1_a-p.m3u8?sd=10&rebase=on"
                },
                {
                    "name": "Mirchi Telugu Love",
                    "language": "Hindi",
                    "band": "Online",
                    "location": "Radio Mirchi",
                    "image": "https://a10.gaanacdn.com/gn_img/m_radio_circle/zLp36v3rGe/zLp36v3rGe/size_l_1563783975.webp",
                    "url": "https://mirchilovetelugu-lh.akamaihd.net/i/Mirchi_love_telugu_1@504635/master.m3u8"
                },
                {
                    "name": "Mirchi English Love",
                    "language": "Hindi",
                    "band": "Online",
                    "location": "Radio Mirchi",
                    "image": "https://media.radiomirchi.com/onlinestation/banners/EnglishLove662.jpg",
                    "url": "https://radioromancehdli-lh.akamaihd.net/i/RadioRomanceHDLive_1_1@334956/index_1_a-p.m3u8?sd=10&rebase=on"
                },
                {
                    "name": "Mirchi English Retro",
                    "language": "Hindi",
                    "band": "Online",
                    "location": "Radio Mirchi",
                    "image": "https://media.radiomirchi.com/onlinestation/banners/EnglishRetro874.jpg",
                    "url": "https://cassetteclassics-lh.akamaihd.net/i/CassClassicsHDLive_1_1@334553/index_1_a-p.m3u8?sd=10&rebase=on"
                },
                {
                    "name": "Radio Mirchi",
                    "language": "Hindi",
                    "band": "98.3 FM",
                    "location": "All India",
                    "image": "https://1.bp.blogspot.com/-p8YmsWF2yHo/X-dgCQhC31I/AAAAAAAAAYI/Lgt6YWus4EY3CG4H3OqVEzf7Ur4oXNFnQCLcBGAsYHQ/s320/98.3fm.jpg",
                    "url": "https://s3.radio.co/se787a5a6f/listen"
                }
            ]
        },
        {
            "item_name": "Hungama Radio",
            "item_img": "https://pbs.twimg.com/profile_images/1250140323876986880/kBUg2X1-.jpg",
            "item_station": [
                {
                    "name": "Hungama 90s Once Again",
                    "language": "Hindi",
                    "band": "online",
                    "location": "Hungama, Mumbai",
                    "image": "https://mytuner.global.ssl.fastly.net/media/tvos_radios/sgjkrL4YeY.jpeg",
                    "url": "https://securestreams8.autopo.st:3003/1"
                },
                {
                    "name": "Hungama Bollywood Dil Se",
                    "language": "Hindi",
                    "band": "Online",
                    "location": "Hungama, Mumbai",
                    "image": "https://liveradios.in/wp-content/uploads/bollywooddilse.jpg",
                    "url": "https://securestreams8.autopo.st:3001/1"
                },
                {
                    "name": "Hungama Hot Now Bollywood",
                    "language": "Hindi",
                    "band": "Online",
                    "location": "Hungama",
                    "image": "https://static.tuneyou.com/images/logos/500_500/46/12546/HungamaHotNowBollywood_9.jpg",
                    "url": "https://securestreams8.autopo.st:3027/1"
                },
                {
                    "name": "Hungama Evergreen Bollywood",
                    "language": "Hindi",
                    "band": "Online",
                    "location": "Hungama, Mumbai",
                    "image": "https://liveradios.in/wp-content/uploads/evergreenbollywood.jpg",
                    "url": "https://securestreams8.autopo.st:3002/1"
                },
                {
                    "name": "Hungama Best of Indie Pop",
                    "language": "Hindi",
                    "band": "Online",
                    "location": "Hungama, Mumbai",
                    "image": "https://liveonlineradio.net/wp-content/uploads/2021/03/hungama-best-of-indie-pop.jpg",
                    "url": "https://securestreams8.autopo.st:3004/1"
                },
                {
                    "name": "Hungama Dance Masti Bollywood",
                    "language": "Hindi",
                    "band": "Online",
                    "location": "Hungama, Mumbai",
                    "image": "https://dev-resws-hungamatech-com.storage.googleapis.com/featured_content/e419f2f0b89fdcd00bbb2f76c142693b_500x500.jpg",
                    "url": "https://securestreams8.autopo.st:3005/1"
                },
                {
                    "name": "Hungama Bhakti Sagar",
                    "language": "Hindi",
                    "band": "Online",
                    "location": "Hungama, Mumbai",
                    "image": "https://static.mytuner.mobi/media/tvos_radios/gUnPyeckBn.jpeg",
                    "url": "https://securestreams8.autopo.st:3006/1"
                },
                {
                    "name": "Hungama Best of Ghazals",
                    "language": "Hindi",
                    "band": "Online",
                    "location": "Hungama, Mumbai",
                    "image": "https://liveonlineradio.net/wp-content/uploads/2021/03/hungama-best-of-ghazals.jpg",
                    "url": "https://securestreams8.autopo.st:3007/1"
                },
                {
                    "name": "Hungama Bollywood Instrumentals",
                    "language": "Hindi",
                    "band": "Online",
                    "location": "Hungama, Mumbai",
                    "image": "https://static.mytuner.mobi/media/tvos_radios/Vebq3LKJRM.jpeg",
                    "url": "https://securestreams8.autopo.st:3008/1"
                },
                {
                    "name": "Hungama Best Of Spiritual",
                    "language": "Hindi",
                    "band": "Online",
                    "location": "Hungama, Mumbai",
                    "image": "https://www.radioindialive.com/uploads/radios/Spiritual%20Radio.jpg",
                    "url": "http://103.16.47.70:7000/;stream.nsv"
                },
                {
                    "name": "Hungama Artist Aloud",
                    "language": "Hindi",
                    "band": "Online",
                    "location": "Hungama, Mumbai",
                    "image": "http://www.radioandmusic.com/sites/www.radioandmusic.com/files/styles/490x490/public/images/biz/2019/03/14/Artist-Aloud---New-Logo-1.jpg?itok=1hH6vmOJ",
                    "url": "https://securestreams8.autopo.st:3010/1"
                },
                {
                    "name": "Hungama Hindustani Classical",
                    "language": "Hindi",
                    "band": "Online",
                    "location": "Hungama",
                    "image": "https://www.radioindialive.com//uploads/radios/Hindustani%20Classical%20Radio.jpg",
                    "url": "https://securestreams8.autopo.st:3011/1"
                },
                {
                    "name": "Hungama B&W Classics",
                    "language": "Hindi",
                    "band": "Online",
                    "location": "Hungama",
                    "image": "https://liveonlineradio.net/wp-content/uploads/2021/03/hungama-bw-classics.jpg",
                    "url": "https://securestreams8.autopo.st:3022/1"
                },
                {
                    "name": "Hungama 60s Forever",
                    "language": "Hindi",
                    "band": "Online",
                    "location": "Hungama",
                    "image": "https://www.radioindialive.com//uploads/radios/60s%20Forever.jpg",
                    "url": "https://securestreams8.autopo.st:3023/1"
                },
                {
                    "name": "Hungama Hot Now Punjabi",
                    "language": "Punjabi",
                    "band": "Online",
                    "location": "Hungama",
                    "image": "https://www.radioindialive.com//uploads/radios/Punjabi%20Radio.jpg",
                    "url": "https://securestreams8.autopo.st:3019/1"
                },
                {
                    "name": "Hungama Hot Now International",
                    "language": "English",
                    "band": "Online",
                    "location": "Hungama",
                    "image": "https://dev-resws-hungamatech-com.storage.googleapis.com/featured_content/68ad307316e623c6fb9e22c3897d9d66_200x200.jpg",
                    "url": "https://securestreams8.autopo.st:3012/1"
                },
                {
                    "name": "Hungama Hindi Bollywood",
                    "language": "English",
                    "band": "Online",
                    "location": "Hungama",
                    "image": "https://static.wikia.nocookie.net/logopedia/images/3/35/Hungama_TV.png/revision/latest?cb=20111015213235",
                    "url": "https://radioindia.net/radio/humgama-telugu/icecast.audio"
                },
                {
                    "name": "Hungama Evergreen International",
                    "language": "English",
                    "band": "Online",
                    "location": "Hungama",
                    "image": "https://dev-resws-hungamatech-com.storage.googleapis.com/featured_content/f876caef45c2c1c2217b709a27970f06_200x200.jpg",
                    "url": "https://securestreams8.autopo.st:3013/1"
                },
                {
                    "name": "Hungama Best of EDM",
                    "language": "English",
                    "band": "Online",
                    "location": "Hungama",
                    "image": "https://liveonlineradio.net/wp-content/uploads/2021/03/hungama-best-of-edm.jpg",
                    "url": "https://securestreams8.autopo.st:3015/1"
                },
                {
                    "name": "Hungama Hot Now Tamil",
                    "band": "Online",
                    "language": "Tamil",
                    "location": "Hungama",
                    "image": "https://onlineradiofm.in/assets/image/radio/180/hot-now-tamil.jpg",
                    "url": "https://securestreams8.autopo.st:3020/1"
                },
                {
                    "name": "Hungama Tamil Romantic",
                    "band": "Online",
                    "language": "Tamil",
                    "location": "Hungama",
                    "image": "https://dev-resws-hungamatech-com.storage.googleapis.com/featured_content/3fb09aab4aeb2b763afa7c00e6c83f0d_200x200.jpg",
                    "url": "https://securestreams8.autopo.st:3026/1"
                },
                {
                    "name": "Hungama Evergreen Tamil",
                    "band": "Online",
                    "language": "Tamil",
                    "location": "Hungama",
                    "image": "https://dev-resws-hungamatech-com.storage.googleapis.com/featured_content/576633194f32a573c4eff6b2081471be_200x200.jpg",
                    "url": "https://securestreams8.autopo.st:3016/1"
                },
                {
                    "name": "Hungama Hot Now Telugu",
                    "band": "Online",
                    "language": "Telugu",
                    "location": "Hungama",
                    "image": "https://www.radioindialive.com/uploads/social/Telugu%20Radio.jpg",
                    "url": "https://securestreams8.autopo.st:3018/1"
                },
                {
                    "name": "Hungama Hot Now Kannada",
                    "band": "Online",
                    "language": "Kannada",
                    "location": "Hungama",
                    "image": "https://dev-resws-hungamatech-com.storage.googleapis.com/featured_content/ce1e59a8c15bf631e9881b45d1f2978b_200x200.jpg",
                    "url": "https://securestreams8.autopo.st:3017/1"
                },
                {
                    "name": "Hungama Kannada Romantic",
                    "band": "Online",
                    "language": "Kannada",
                    "location": "Hungama",
                    "image": "https://dev-resws-hungamatech-com.storage.googleapis.com/featured_content/3948ae871698234a4690e72be5e60f18_200x200.jpg",
                    "url": "https://securestreams8.autopo.st:3025/1"
                },
                {
                    "name": "Hungama Carnatic Classical",
                    "band": "Online",
                    "language": "Kannada",
                    "location": "Hungama",
                    "image": "https://static.wikia.nocookie.net/logopedia/images/3/35/Hungama_TV.png/revision/latest?cb=20111015213235",
                    "url": "https://securestreams8.autopo.st:3021/1"
                },
                {
                    "name": "Hungama Hot Now Bangla",
                    "band": "Online",
                    "language": "Bengali",
                    "location": "Hungama",
                    "image": "https://liveonlineradio.net/wp-content/uploads/2021/03/hungama-hot-now-bangla.jpg",
                    "url": "https://securestreams8.autopo.st:3024/1"
                },
                {
                    "name": "Hungama Dance Masti International",
                    "language": "English",
                    "band": "Online",
                    "location": "Hungama",
                    "image": "https://dev-resws-hungamatech-com.storage.googleapis.com/featured_content/c04c1eb6a7cbd0b6acda31950073dc5e_200x200.jpg",
                    "url": "https://securestreams8.autopo.st:3014/1"
                }
            ]
        },
        {
            "item_name": "Radio City",
            "item_img": "https://upload.wikimedia.org/wikipedia/en/thumb/b/bd/Radio_City_Logo.jpg/220px-Radio_City_Logo.jpg",
            "item_station": [
                {
                    "name": "Radio City Hindi",
                    "language": "Hindi",
                    "band": "City FM",
                    "location": "Radio City, Mumbai",
                    "image": "https://www.radiocity.in/images/uploads/hindi_l.jpg",
                    "url": "https://prclive4.listenon.in/Hindi"
                },
                {
                    "name": "Radio City (Love Guru)",
                    "language": "Hindi",
                    "band": "91.1 FM",
                    "location": "Delhi",
                    "image": "https://1.bp.blogspot.com/-n4y3mgKjdbs/X-djcKGCSlI/AAAAAAAAAYk/KNdHqbAm94MU-1cOdc4b-8s2WCZXsBapQCLcBGAsYHQ/s320/65404_radio-city-love-guru.png.png",
                    "url": "https://prclive4.listenon.in/Ishq"
                },
                {
                    "name": "Radio City Premaloka",
                    "language": "Kannada",
                    "band": "91.1 FM",
                    "location": "Radio City, Mumbai",
                    "image": "https://www.radiocity.in/images/uploads/premaloka_l.jpg",
                    "url": "https://prclive4.listenon.in/Premaloka"
                },
                {
                    "name": "Radio City Kannada",
                    "language": "Kannada",
                    "band": "91.1 FM",
                    "location": "Radio City, Mumbai",
                    "image": "https://www.radiocity.in/images/uploads/kannada_l.jpg",
                    "url": "https://prclive4.listenon.in/Kannada"
                },
                {
                    "name": "Radio City Tamil",
                    "language": "Tamil",
                    "band": "91.1 FM",
                    "location": "Radio City, Tamilnadu",
                    "image": "https://www.radiocity.in/images/uploads/tamil_l.jpg",
                    "url": "https://prclive4.listenon.in/Tamil"
                },
                {
                    "name": "Radio City Ghazal",
                    "language": "Hindi",
                    "band": "City FM",
                    "location": "Radio City, Mumbai",
                    "image": "https://www.radiocity.in/images/uploads/ghazal_l.jpg",
                    "url": "https://prclive4.listenon.in/Ghazal"
                },
                {
                    "name": "Love Guru Bhojpuri",
                    "language": "Bhojpuri",
                    "band": "City FM",
                    "location": "Radio City, Bihar",
                    "image": "https://www.radiocity.in/images/uploads/lovegurubhojpuri_l.jpg",
                    "url": "https://prclive4.listenon.in/Bhojpuri"
                },
                {
                    "name": "Radio City Freedom",
                    "language": "Hindi",
                    "band": "City FM",
                    "location": "Radio City, Mumbai",
                    "image": "https://www.radiocity.in/images/uploads/freedom_l.jpg",
                    "url": "https://prclive4.listenon.in/Freedom"
                },
                {
                    "name": "Radio City Metal",
                    "language": "Non-Indian",
                    "band": "City FM",
                    "location": "Radio City, Mumbai",
                    "image": "https://www.radiocity.in/images/uploads/metal_l.jpg",
                    "url": "https://prclive4.listenon.in/Metal"
                },
                {
                    "name": "Radio City Electronica",
                    "language": "Non-Indian",
                    "band": "City FM",
                    "location": "Radio City, Mumbai",
                    "image": "https://www.radiocity.in/images/uploads/electronica_l.jpg",
                    "url": "https://prclive4.listenon.in/Electronica"
                },
                {
                    "name": "Radio City Hip Hop",
                    "language": "Hindi",
                    "band": "City FM",
                    "location": "Radio City, Mumbai",
                    "image": "https://www.radiocity.in/images/uploads/hiphop_l.jpg",
                    "url": "https://prclive4.listenon.in/HipHop"
                },
                {
                    "name": "Radio City Punjabi",
                    "language": "Punjabi",
                    "band": "City FM",
                    "location": "Radio City, Mumbai",
                    "image": "https://www.radiocity.in/images/uploads/punjabi_l.jpg",
                    "url": "https://prclive4.listenon.in/Punjabi"
                },
                {
                    "name": "Radio City Dance",
                    "language": "Hindi",
                    "band": "City FM",
                    "location": "Radio City, Mumbai",
                    "image": "https://www.radiocity.in/images/uploads/dance_l.jpg",
                    "url": "https://prclive4.listenon.in/Dance"
                },
                {
                    "name": "Radio City Smaran",
                    "language": "Hindi",
                    "band": "City FM",
                    "location": "Radio City, Mumbai",
                    "image": "https://www.radiocity.in/images/uploads/smaran_l.jpg",
                    "url": "https://prclive4.listenon.in/Smaran"
                },
                {
                    "name": "Radio City Faith",
                    "language": "Tamil",
                    "band": "City FM",
                    "location": "Radio City, Mumbai",
                    "image": "https://www.radiocity.in/images/uploads/faith_l.jpg",
                    "url": "https://prclive4.listenon.in/Faith"
                },
                {
                    "name": "Radio City Bhakti",
                    "language": "Telugu",
                    "band": "91.1 FM",
                    "location": "Radio City, Mumbai",
                    "image": "https://www.radiocity.in/images/uploads/bhaktitelugu_l.jpg",
                    "url": "https://prclive4.listenon.in/Bhakti"
                },
                {
                    "name": "Radio City Gujarati",
                    "language": "Gujrati",
                    "band": "91.1 FM",
                    "location": "Radio City, Ahmdabad",
                    "image": "https://www.radiocity.in/images/uploads/gujarati_l.jpg",
                    "url": "https://prclive4.listenon.in/Gujarati"
                }
            ]
        },
        {
            "item_name": "BBC World Service",
            "item_img": "https://onlineradiofm.in/assets/image/radio/180/BBC-world-servie.png",
            "item_station": [
                
                {
                    "name": "BBC World Service",
                    "image": "https://onlineradiofm.in/assets/image/radio/180/BBC-world-servie.png",
                    "url": "https://stream.live.vc.bbcmedia.co.uk/bbc_world_service",
                    "location": "Great Britain, London",
                    "band": "Web",
                    "language": "English"
                },
                {
                    "name": "BBC Hindi",
                    "image": "https://mytuner.global.ssl.fastly.net/media/radios-150px/NeWjCrQbjG.png",
                    "url": "https://stream.live.vc.bbcmedia.co.uk/bbc_hindi_radio",
                    "location": "NCR",
                    "band": "Web",
                    "language": "Hindi"
                },
                {
                    "name": "BBC Urdu",
                    "image": "https://news.files.bbci.co.uk/ws/img/logos/og/urdu.png",
                    "url": "https://stream.live.vc.bbcmedia.co.uk/bbc_urdu_radio",
                    "location": "London",
                    "band": "Web",
                    "language": "Urdu"
                },
                {
                    "name": "BBC Bangla",
                    "image": "https://news.files.bbci.co.uk/ws/img/logos/og/bengali.png",
                    "url": "https://stream.live.vc.bbcmedia.co.uk/bbc_bangla_radio",
                    "location": "Kolkata, West Bangal, India",
                    "band": "Web",
                    "language": "Bengali"
                },
                {
                    "name": "BBC Nepali",
                    "image": "https://mytuner.global.ssl.fastly.net/media/tvos_radios/nLeR7PKF9j.png",
                    "url": "https://stream.live.vc.bbcmedia.co.uk/bbc_nepali_radio",
                    "location": "Kathmandu, Nepal",
                    "band": "Web",
                    "language": "Nepali"
                },
                {
                    "name": "BBC Tamil",
                    "image": "https://news.files.bbci.co.uk/ws/img/logos/og/tamil.png",
                    "url": "https://stream.live.vc.bbcmedia.co.uk/bbc_tamil_radio",
                    "location": "Tamilnadu, India",
                    "band": "Web",
                    "language": "Tamil"
                },
                {
                    "name": "BBC Radio 1 Live",
                    "image": "https://mytuner.global.ssl.fastly.net/media/tvos_radios/BFcU2vjUXh.png",
                    "url": "https://stream.live.vc.bbcmedia.co.uk/bbc_radio_one",
                    "location": "London, England, UK",
                    "band": "Web",
                    "language": "English"
                },
                {
                    "name": "BBC Radio 2 Live",
                    "image": "https://mytuner.global.ssl.fastly.net/media/tvos_radios/N6JJwvwy9g.png",
                    "url": "https://stream.live.vc.bbcmedia.co.uk/bbc_radio_two",
                    "location": "London, England, UK",
                    "band": "Web",
                    "language": "English"
                },
                {
                    "name": "BBC Radio 3 Live",
                    "image": "https://mytuner.global.ssl.fastly.net/media/tvos_radios/shtS6qMGDF.png",
                    "url": "https://stream.live.vc.bbcmedia.co.uk/bbc_radio_three",
                    "location": "London, England, UK",
                    "band": "Web",
                    "language": "English"
                },
                {
                    "name": "BBC Radio 4 Live",
                    "image": "https://mytuner.global.ssl.fastly.net/media/tvos_radios/NHeXQWMsBh.png",
                    "url": "https://stream.live.vc.bbcmedia.co.uk/bbc_radio_fourfm",
                    "location": "London, England, UK",
                    "band": "Web",
                    "language": "English"
                },
                {
                    "name": "BBC Radio 5 Live",
                    "image": "https://mytuner.global.ssl.fastly.net/media/tvos_radios/EgCmT9UNSr.png",
                    "url": "http://stream.live.vc.bbcmedia.co.uk/bbc_radio_five_live_online_nonuk",
                    "location": "London, England, UK",
                    "band": "Web",
                    "language": "English"
                },
                {
                    "name": "BBC Radio 5 Live Sports Extra",
                    "image": "https://mytuner.global.ssl.fastly.net/media/tvos_radios/jNFcZfxdwS.png",
                    "url": "https://stream.live.vc.bbcmedia.co.uk/bbc_radio_five_live_sports_extra",
                    "location": "London, England, UK",
                    "band": "Web",
                    "language": "English"
                },
                {
                    "name": "BBC Radio 4 Extra",
                    "image": "https://mytuner.global.ssl.fastly.net/media/tvos_radios/2kxpnsRvzm.png",
                    "url": "http://stream.live.vc.bbcmedia.co.uk/bbc_radio_four_extra",
                    "location": "London, England, UK",
                    "band": "Web",
                    "language": "English"
                },
                {
                    "name": "BBC Asian Network",
                    "image": "https://mytuner.global.ssl.fastly.net/media/tvos_radios/cRqAAWNnbV.png",
                    "url": "https://stream.live.vc.bbcmedia.co.uk/bbc_asian_network",
                    "location": "London, England, UK",
                    "band": "Web",
                    "language": "English"
                },
                {
                    "name": "BBC 1Xtra",
                    "image": "https://mytuner.global.ssl.fastly.net/media/tvos_radios/89MJWuCrEF.png",
                    "url": "https://stream.live.vc.bbcmedia.co.uk/bbc_radio_five_live_sports_extra",
                    "location": "London, England, UK",
                    "band": "Web",
                    "language": "English"
                },
                {
                    "name": "BBC 6 Music",
                    "image": "https://mytuner.global.ssl.fastly.net/media/tvos_radios/ZjeeuBNXRP.png",
                    "url": "http://stream.live.vc.bbcmedia.co.uk/bbc_6music",
                    "location": "London, England, UK",
                    "band": "Web",
                    "language": "English"
                },
                {
                    "name": "BBC Hausa",
                    "image": "https://mytuner.global.ssl.fastly.net/media/tvos_radios/3WtmyLbPuq.png",
                    "url": "https://stream.live.vc.bbcmedia.co.uk/bbc_hausa_radio",
                    "location": "London, England, UK",
                    "band": "Web",
                    "language": "Hausa"
                },
                {
                    "name": "BBC Swahili",
                    "image": "https://mytuner.global.ssl.fastly.net/media/tvos_radios/uvjs7m6495cs.jpg",
                    "url": "https://stream.live.vc.bbcmedia.co.uk/bbc_swahili_radio",
                    "location": "London, England, UK",
                    "band": "Web",
                    "language": "Swahili"
                },
                {
                    "name": "BBC Radio Scotland",
                    "image": "https://mytuner.global.ssl.fastly.net/media/tvos_radios/jkg2cpbbqud3.png",
                    "url": "http://stream.live.vc.bbcmedia.co.uk/bbc_radio_scotland_fm",
                    "location": "London, England, UK",
                    "band": "Web",
                    "language": "English"
                },
                {
                    "name": "BBC Arabic",
                    "image": "https://cdn.onlineradiobox.com/img/l/6/1196.v7.png",
                    "url": "https://stream.live.vc.bbcmedia.co.uk/bbc_arabic_radio",
                    "location": "London, England, UK",
                    "band": "Web",
                    "language": "Arabic"
                },
                {
                    "name": "BBC Persian",
                    "image": "https://news.files.bbci.co.uk/ws/img/logos/og/persian.png",
                    "url": "https://stream.live.vc.bbcmedia.co.uk/bbc_persian",
                    "location": "London, England, UK",
                    "band": "Web",
                    "language": "English"
                }
                
            ]
        },
        {
            "item_name":"Exclusive Radio",
            "item_img":"https://mytuner.global.ssl.fastly.net/media/tvos_radios/3dte8qezghgd.png",
            "item_station":[
                {
                    "name": "Bollywood Mix",
                    "image": "https://manager.uber.radio/static/uploads/station/e9e5b243-51c0-421e-91ea-3ee3487d40cd.png",
                    "url": "https://drive.uber.radio/uber/bollywoodmix/icecast.audio",
                    "location": "Online",
                    "band": "Web",
                    "language": "Hindi"
                },{
                    "name": "Bollywood Dance",
                    "image": "https://manager.uber.radio/static/uploads/station/7859c249-fc56-4867-9ee5-85250140920c.png",
                    "url": "https://drive.uber.radio/uber/bollywooddance/icecast.audio",
                    "location": "Online",
                    "band": "Web",
                    "language": "Hindi"
                },{
                    "name": "Bollywood Diwali PartyMix",
                    "image": "https://manager.uber.radio/static/uploads/station/1759d229-40cb-4322-b2cf-afeb4197a6c5.png",
                    "url": "https://drive.uber.radio/uber/bollywooddiwali/icecast.audio",
                    "location": "Online",
                    "band": "Web",
                    "language": "Hindi"
                },{
                    "name": "Bollywood Love",
                    "image": "https://manager.uber.radio/static/uploads/station/c8732324-4b45-423d-8ddf-1d58bea699bc.png",
                    "url": "https://drive.uber.radio/uber/bollywoodlove/icecast.audio",
                    "location": "Online",
                    "band": "Web",
                    "language": "Hindi"
                },{
                    "name": "Bollywood Now",
                    "image": "https://manager.uber.radio/static/uploads/station/1759d229-40cb-4322-b2cf-afeb4197a6c5.png",
                    "url": "https://drive.uber.radio/uber/bollywoodnow/icecast.audio",
                    "location": "Online",
                    "band": "Web",
                    "language": "Hindi"
                },{
                    "name": "Bollywood Work Out",
                    "image": "https://manager.uber.radio/static/uploads/station/795cf052-6f2f-4d06-a8ff-1d913c938a34.png",
                    "url": "https://drive.uber.radio/uber/bollywoodworkout/icecast.audio",
                    "location": "Online",
                    "band": "Web",
                    "language": "Hindi"
                },{
                    "name": "Bollywood 2010's",
                    "image": "https://manager.uber.radio/static/uploads/station/e9e5b243-51c0-421e-91ea-3ee3487d40cd.png",
                    "url": "https://drive.uber.radio/uber/bollywood2010s/icecast.audio",
                    "location": "Online",
                    "band": "Web",
                    "language": "Hindi"
                },{
                    "name": "TikTok Trending ",
                    "image": "https://manager.uber.radio/static/uploads/station/aa9b4f8e-e4cc-4bc1-a58c-75fde4e99bf6.jpg",
                    "url": "https://drive.uber.radio/uber/tiktoktrending/icecast.audio",
                    "location": "Online",
                    "band": "Web",
                    "language": "Hindi"
                }
            ]
        },
        {
            "item_name": "Goldy Radio",
            "item_img": "https://images-na.ssl-images-amazon.com/images/I/61M8p4indiL.png",
            "item_station": [
                {
                    "name": "Goldy Gujrati",
                    "language": "Gujrati",
                    "band": "Goldy FM",
                    "location": "Gujrat",
                    "image": "https://mytuner.global.ssl.fastly.net/media/tvos_radios/xqywneqdfkps.png",
                    "url": "https://stream.zeno.fm/hrtamh18am8uv"
                },
                {
                    "name": "Goldy Garba",
                    "language": "Gujrat",
                    "band": "Goldy FM",
                    "location": "Gujrat",
                    "image": "https://mytuner.global.ssl.fastly.net/media/tvos_radios/wkj6jrdaquuj.png",
                    "url": "https://stream.zeno.fm/by0808wa6p8uv"
                },
                {
                    "name": "Goldy Cool",
                    "language": "Hindi",
                    "band": "Goldy FM",
                    "location": "Gujrat",
                    "image": "https://mytuner.global.ssl.fastly.net/media/tvos_radios/gjcph55dnnrz.png",
                    "url": "https://stream.zeno.fm/hhfmh86tfm8uv"
                },
                {
                    "name": "Goldy Blast",
                    "language": "Hindi",
                    "band": "Goldy FM",
                    "location": "Radio Goldy",
                    "image": "https://mytuner.global.ssl.fastly.net/media/tvos_radios/pn4demyuu2sy.png",
                    "url": "https://stream.zeno.fm/d0rwvvwa6p8uv"
                },
                {
                    "name": "Goldy Sarvaani",
                    "language": "Gujrati",
                    "band": "Goldy FM",
                    "location": "Radio Goldy",
                    "image": "https://mytuner.global.ssl.fastly.net/media/tvos_radios/rrttn8aewj3g.png",
                    "url": "https://stream.zeno.fm/8ze2dk37bm8uv"
                },
                {
                    "name": "Goldy Aaradhna",
                    "language": "Gujrat",
                    "band": "Goldy FM",
                    "location": "Gujrat",
                    "image": "https://mytuner.global.ssl.fastly.net/media/tvos_radios/sqyemxzbftda.png",
                    "url": "https://stream.zeno.fm/4kywc9r2cm8uv"
                },
                {
                    "name": "Goldy Bhal",
                    "language": "Hindi",
                    "band": "Goldy FM",
                    "location": "Radio Goldy",
                    "image": "https://mytuner.global.ssl.fastly.net/media/tvos_radios/kk88nvvjd7rs.png",
                    "url": "https://stream.zeno.fm/rfxzab5h3p8uv"
                },
                {
                    "name": "Goldy Mukesh",
                    "language": "Hindi",
                    "band": "Goldy FM",
                    "location": "Radio Goldy",
                    "image": "https://mytuner.global.ssl.fastly.net/media/tvos_radios/wxktvurhesyj.png",
                    "url": "https://stream.zeno.fm/t39watus1p8uv"
                },
                {
                    "name": "Goldy Evergreen",
                    "language": "Hindi",
                    "band": "Goldy FM",
                    "location": "Radio Goldy",
                    "image": "https://mytuner.global.ssl.fastly.net/media/tvos_radios/khbf2jlccjaf.png",
                    "url": "https://stream.zeno.fm/kpbedgdh9k8uv"
                }
            ]
        }
    ]
}
